zpipe/__init__.py
zpipe/codec.py
zpipe/exception.py
zpipe/pipe.py
zpipe/pipe_server.py
zpipe/plugin_base.py
zpipe/codec_plugin/__init__.py
zpipe/codec_plugin/zpipe_codec_dict.py
zpipe/codec_plugin/zpipe_codec_json.py
zpipe/codec_plugin/zpipe_codec_msgpack.py
zpipe/codec_plugin/zpipe_codec_raw.py
zpipe/filter_plugin/__init__.py
zpipe/filter_plugin/zpipe_filter_default.py
zpipe/output_plugin/__init__.py
zpipe/output_plugin/zpipe_output_log.py
zpipe-0.0.1.dist-info/LICENSE
zpipe-0.0.1.dist-info/METADATA
zpipe-0.0.1.dist-info/WHEEL
zpipe-0.0.1.dist-info/top_level.txt
zpipe-0.0.1.dist-info/RECORD
