Metadata-Version: 2.1
Name: zpipe
Version: 0.0.1
Summary: 嵌入式管道模块, 类似于logstash
Home-page: https://pypi.org/project/zpipe/
Author: zlyuan
Author-email: 1277260932@qq.com
License: GNU GENERAL PUBLIC LICENSE
Platform: all
Classifier: Environment :: Web Environment
Classifier: Intended Audience :: Developers
Classifier: Operating System :: OS Independent
Classifier: Programming Language :: Python :: 3
Requires-Dist: msgpack (>=0.6.1)
Requires-Dist: zlogger
